setup.py
milight/__init__.py
milight/rgb.py
milight/rgbw.py
milight/white.py
milight.egg-info/PKG-INFO
milight.egg-info/SOURCES.txt
milight.egg-info/dependency_links.txt
milight.egg-info/top_level.txt