Metadata-Version: 1.1
Name: milight
Version: 0.5.1
Summary: Controller for milight/limitlessled Wi-Fi LEDs
Home-page: https://github.com/McSwindler/python-milight
Author: McSwindler
Author-email: wilingua@gmail.com
License: MIT
Keywords: limitlessled easybulb milight led wifi applight applamp ledme dekolight ilight
Platform: UNKNOWN
Classifier: Development Status :: 4 - Beta
Classifier: Topic :: Home Automation
Classifier: Intended Audience :: Developers
Classifier: License :: OSI Approved :: MIT License
Classifier: Programming Language :: Python :: 2.7
Classifier: Programming Language :: Python :: 3
Classifier: Programming Language :: Python :: 3.2
Classifier: Programming Language :: Python :: 3.3
Classifier: Programming Language :: Python :: 3.4
